showquota/__init__.py
showquota/__main__.py
showquota/__version__.py
showquota/config.cfg
showquota/config.py
showquota/main.py
showquota/showquota.py
showquota-1.0.4.dist-info/LICENSE
showquota-1.0.4.dist-info/METADATA
showquota-1.0.4.dist-info/WHEEL
showquota-1.0.4.dist-info/entry_points.txt
showquota-1.0.4.dist-info/top_level.txt
showquota-1.0.4.dist-info/RECORD
