Metadata-Version: 2.1
Name: showquota
Version: 1.0.4
Summary: Show user and projects storage quotas.
Home-page: https://github.com/giuliolibrando/showquota
Author: Giulio Librando
Author-email: giuliolibrando@gmail.com
License: MIT
Platform: UNKNOWN
Classifier: Programming Language :: Python :: 3
Classifier: License :: OSI Approved :: MIT License
Classifier: Operating System :: OS Independent
License-File: LICENSE
Requires-Dist: paramiko
